instagram_auth/__init__.py
instagram_auth/common/PasswordUtils.py
instagram_auth/common/__init__.py
instagram_auth/common/exception/__init__.py
instagram_auth/common/exception/web/CSRFTokenException.py
instagram_auth/common/exception/web/InstagramLoginNonceException.py
instagram_auth/common/exception/web/InstagramSessionExpiredException.py
instagram_auth/common/exception/web/InstagramSignInException.py
instagram_auth/common/exception/web/ResponseException.py
instagram_auth/common/exception/web/__init__.py
instagram_auth/common/model/InstagramShortUser.py
instagram_auth/common/model/__init__.py
instagram_auth/service/WebLoginService.py
instagram_auth/service/__init__.py
instagram_auth-0.1.5.dist-info/LICENSE
instagram_auth-0.1.5.dist-info/METADATA
instagram_auth-0.1.5.dist-info/WHEEL
instagram_auth-0.1.5.dist-info/RECORD
