Metadata-Version: 2.1
Name: instagram-auth
Version: 0.1.5
Summary: Instagram Web Auth
Home-page: https://gitlab.com/bitt_moe/instagram/auth.git
Author: Николай Витальевич Никоноров
Author-email: nnv@bitt.moe
Requires-Python: >=3.10,<4.0
Classifier: Programming Language :: Python :: 3
Classifier: Programming Language :: Python :: 3.10
Classifier: Programming Language :: Python :: 3.11
Classifier: Programming Language :: Python :: 3.12
Classifier: Programming Language :: Python :: 3.13
Requires-Dist: PyNaCl (==1.5.0)
Requires-Dist: aiohappyeyeballs (==2.4.3)
Requires-Dist: aiohttp (==3.10.9)
Requires-Dist: aiosignal (==1.3.1)
Requires-Dist: async-timeout (==4.0.3)
Requires-Dist: attrs (==24.2.0)
Requires-Dist: cffi (==1.16.0)
Requires-Dist: frozenlist (==1.4.1)
Requires-Dist: idna (==3.10)
Requires-Dist: multidict (==6.1.0)
Requires-Dist: pycparser (==2.21)
Requires-Dist: pycryptodomex (==3.19.1)
Requires-Dist: typing_extensions (==4.12.2)
Requires-Dist: yarl (==1.13.1)
Project-URL: Repository, https://gitlab.com/bitt_moe/instagram/auth.git
